tinybig/__init__.py
tinybig/compression/__init__.py
tinybig/compression/basic_compression.py
tinybig/compression/combinatorial_compression.py
tinybig/compression/dimension_reduction_compression.py
tinybig/compression/extended_compression.py
tinybig/compression/feature_selection_compression.py
tinybig/compression/geometric_compression.py
tinybig/compression/manifold_compression.py
tinybig/compression/metric_based_compression.py
tinybig/compression/nested_compression.py
tinybig/compression/probabilistic_compression.py
tinybig/config/__init__.py
tinybig/config/base_config.py
tinybig/config/data_configs.py
tinybig/config/function_configs.py
tinybig/config/fusion_configs.py
tinybig/config/head_configs.py
tinybig/config/interdependence_configs.py
tinybig/config/layer_configs.py
tinybig/config/learner_configs.py
tinybig/config/metric_configs.py
tinybig/config/model_configs.py
tinybig/config/output_configs.py
tinybig/config/reconciliation_configs.py
tinybig/config/remainder_configs.py
tinybig/config/transformation_configs.py
tinybig/data/__init__.py
tinybig/data/base_data.py
tinybig/data/feynman_dataloader.py
tinybig/data/function_dataloader.py
tinybig/data/graph_dataloader.py
tinybig/data/tabular_dataloader.py
tinybig/data/text_dataloader_huggingface.py
tinybig/data/text_dataloader_torchtext.py
tinybig/data/time_series_dataloader.py
tinybig/data/vision_dataloader.py
tinybig/expansion/__init__.py
tinybig/expansion/basic_expansion.py
tinybig/expansion/combinatorial_expansion.py
tinybig/expansion/extended_expansion.py
tinybig/expansion/geometric_expansion.py
tinybig/expansion/nested_expansion.py
tinybig/expansion/orthogonal_polynomial_expansion.py
tinybig/expansion/polynomial_expansion.py
tinybig/expansion/probabilistic_expansion.py
tinybig/expansion/rbf_expansion.py
tinybig/expansion/recursive_expansion.py
tinybig/expansion/trigonometric_expansion.py
tinybig/expansion/wavelet_expansion.py
tinybig/fusion/__init__.py
tinybig/fusion/basic_fusion.py
tinybig-0.2.1.dist-info/LICENSE
tinybig-0.2.1.dist-info/METADATA
tinybig-0.2.1.dist-info/WHEEL
tinybig-0.2.1.dist-info/top_level.txt
tinybig-0.2.1.dist-info/RECORD
