Metadata-Version: 2.1
Name: tinybig
Version: 0.2.1
Summary: tinybig library for deep function learning
Home-page: https://www.tinybig.org
Download-URL: https://github.com/jwzhanggy/tinyBIG
Author: Jiawei Zhang
Author-email: jiawei@ifmlab.org
License: MIT License
Keywords: tinybig,rpn,deep function learning,data transformation function,data interdependence function,parameter reconciliation function,remainder function,reconciled polynomial network
Classifier: Programming Language :: Python :: 3
Classifier: License :: OSI Approved :: MIT License
Classifier: Operating System :: OS Independent
Requires-Python: >=3.10
License-File: LICENSE
Requires-Dist: torch==2.2.2
Requires-Dist: torchdata==0.7.1
Requires-Dist: torchvision==0.17.2
Requires-Dist: torchtext==0.17.2
Requires-Dist: portalocker==2.10.0
Requires-Dist: numpy==1.26.3
Requires-Dist: scipy==1.13.1
Requires-Dist: scikit-learn==1.5.1
Requires-Dist: pyyaml==6.0.1
Requires-Dist: tqdm==4.66.4
Requires-Dist: matplotlib==3.9.1
Requires-Dist: pytest==8.3.3
